MANIFEST.in
setup.cfg
setup.py
ckanext/__init__.py
ckanext/datarequests/__init__.py
ckanext/datarequests/actions.py
ckanext/datarequests/auth.py
ckanext/datarequests/constants.py
ckanext/datarequests/db.py
ckanext/datarequests/helpers.py
ckanext/datarequests/plugin.py
ckanext/datarequests/validator.py
ckanext/datarequests/controllers/__init__.py
ckanext/datarequests/controllers/ui_controller.py
ckanext/datarequests/fanstatic/.DS_Store
ckanext/datarequests/fanstatic/edit_comment.js
ckanext/datarequests/i18n/ckanext-datarequests.pot
ckanext/datarequests/i18n/de/LC_MESSAGES/ckanext-datarequests.mo
ckanext/datarequests/i18n/de/LC_MESSAGES/ckanext-datarequests.po
ckanext/datarequests/i18n/es/LC_MESSAGES/ckanext-datarequests.mo
ckanext/datarequests/i18n/es/LC_MESSAGES/ckanext-datarequests.po
ckanext/datarequests/i18n/pt_BR/LC_MESSAGES/ckanext-datarequests.mo
ckanext/datarequests/i18n/pt_BR/LC_MESSAGES/ckanext-datarequests.po
ckanext/datarequests/i18n/so/LC_MESSAGES/ckanext-datarequests.po
ckanext/datarequests/public/.DS_Store
ckanext/datarequests/public/datarequests.css
ckanext/datarequests/templates/.DS_Store
ckanext/datarequests/templates/header.html
ckanext/datarequests/templates/datarequests/base.html
ckanext/datarequests/templates/datarequests/close.html
ckanext/datarequests/templates/datarequests/comment.html
ckanext/datarequests/templates/datarequests/edit.html
ckanext/datarequests/templates/datarequests/index.html
ckanext/datarequests/templates/datarequests/new.html
ckanext/datarequests/templates/datarequests/show.html
ckanext/datarequests/templates/datarequests/snippets/additional_info.html
ckanext/datarequests/templates/datarequests/snippets/badge.html
ckanext/datarequests/templates/datarequests/snippets/close_datarequest_form.html
ckanext/datarequests/templates/datarequests/snippets/comment_form.html
ckanext/datarequests/templates/datarequests/snippets/comment_item.html
ckanext/datarequests/templates/datarequests/snippets/comments.html
ckanext_datarequests.egg-info/PKG-INFO
ckanext_datarequests.egg-info/SOURCES.txt
ckanext_datarequests.egg-info/dependency_links.txt
ckanext_datarequests.egg-info/entry_points.txt
ckanext_datarequests.egg-info/namespace_packages.txt
ckanext_datarequests.egg-info/not-zip-safe
ckanext_datarequests.egg-info/top_level.txt