Metadata-Version: 1.1
Name: ckanext-datarequests
Version: 1.1.0
Summary: CKAN Extension - Data Requests
Home-page: https://conwet.fi.upm.es
Author: CoNWeT Lab.
Author-email: amagan@conwet.com
License: GNU Affero General Public License
Download-URL: https://github.com/conwetlab/ckanext-datarequests/tarball/v1.1.0
Platform: UNKNOWN
